pokeapi_ditto/__init__.py
pokeapi_ditto/commands/__init__.py
pokeapi_ditto/commands/analyze.py
pokeapi_ditto/commands/clone.py
pokeapi_ditto/commands/models.py
pokeapi_ditto/commands/transform.py
pokeapi_ditto/common.py
pokeapi_ditto/main.py
pokeapi_ditto-1.0.3.dist-info/LICENSE
pokeapi_ditto-1.0.3.dist-info/METADATA
pokeapi_ditto-1.0.3.dist-info/WHEEL
pokeapi_ditto-1.0.3.dist-info/entry_points.txt
pokeapi_ditto-1.0.3.dist-info/RECORD
