Metadata-Version: 2.1
Name: pokeapi-ditto
Version: 1.0.3
Summary: Ditto is a command line tool for performing meta operations over PokéAPI data.
Home-page: https://github.com/PokeAPI/ditto
License: Apache-2.0
Keywords: pokeapi,ditto,pokemon
Author: Sargun Vohra
Author-email: sargun.vohra@gmail.com
Requires-Python: >=3.10,<4.0
Classifier: Development Status :: 5 - Production/Stable
Classifier: Intended Audience :: Developers
Classifier: License :: OSI Approved :: Apache Software License
Classifier: Programming Language :: Python
Classifier: Programming Language :: Python :: 3
Classifier: Programming Language :: Python :: 3.10
Classifier: Programming Language :: Python :: 3.11
Classifier: Programming Language :: Python :: 3.12
Classifier: Programming Language :: Python :: 3.6
Requires-Dist: genson (>=1.2,<2.0)
Requires-Dist: odictliteral (>=1.0,<2.0)
Requires-Dist: requests (>=2.31,<3.0)
Requires-Dist: tqdm (>=4.66,<5.0)
Requires-Dist: yarl (>=1.9,<2.0)
Project-URL: Documentation, https://github.com/PokeAPI/ditto
Project-URL: Repository, https://github.com/PokeAPI/ditto.git
